setup.py
prodist/Binomialdistribution.py
prodist/Gaussiandistribution.py
prodist/Generaldistribution.py
prodist/__init__.py
prodist.egg-info/PKG-INFO
prodist.egg-info/SOURCES.txt
prodist.egg-info/dependency_links.txt
prodist.egg-info/not-zip-safe
prodist.egg-info/top_level.txt