Metadata-Version: 1.0
Name: prodist
Version: 0.0.1
Summary: probability distributions
Home-page: UNKNOWN
Author: Sagar Tansar
Author-email: myemail@something.com
License: UNKNOWN
Platform: UNKNOWN
